odoo9_addon_web_widget_image_download-9.0.1.0.0.99.dev4-py2.7-nspkg.pth
odoo9_addon_web_widget_image_download-9.0.1.0.0.99.dev4.dist-info/DESCRIPTION.rst
odoo9_addon_web_widget_image_download-9.0.1.0.0.99.dev4.dist-info/METADATA
odoo9_addon_web_widget_image_download-9.0.1.0.0.99.dev4.dist-info/RECORD
odoo9_addon_web_widget_image_download-9.0.1.0.0.99.dev4.dist-info/WHEEL
odoo9_addon_web_widget_image_download-9.0.1.0.0.99.dev4.dist-info/metadata.json
odoo9_addon_web_widget_image_download-9.0.1.0.0.99.dev4.dist-info/namespace_packages.txt
odoo9_addon_web_widget_image_download-9.0.1.0.0.99.dev4.dist-info/top_level.txt
odoo_addons/web_widget_image_download/README.rst
odoo_addons/web_widget_image_download/__init__.py
odoo_addons/web_widget_image_download/__openerp__.py
odoo_addons/web_widget_image_download/i18n/de.po
odoo_addons/web_widget_image_download/i18n/es.po
odoo_addons/web_widget_image_download/i18n/fr.po
odoo_addons/web_widget_image_download/static/description/icon.png
odoo_addons/web_widget_image_download/static/src/css/web_widget_image_download.css
odoo_addons/web_widget_image_download/static/src/js/web_widget_image_download.js
odoo_addons/web_widget_image_download/static/src/xml/web_widget_image_download.xml
odoo_addons/web_widget_image_download/views/assets.xml
