Metadata-Version: 2.0
Name: odoo9-addon-web-widget-image-download
Version: 9.0.1.0.0.99.dev4
Summary: Allows to download any image from its widget
Home-page: https://www.tecnativa.com
Author: Tecnativa, Odoo Community Association (OCA)
Author-email: support@odoo-community.org
License: LGPL-3
Platform: UNKNOWN
Classifier: Programming Language :: Python
Classifier: Framework :: Odoo
Classifier: License :: OSI Approved :: GNU Lesser General Public License v3 (LGPLv3)
Requires-Python: ~=2.7
Requires-Dist: odoo (<9.1a,>=9.0a)
